setup.py
formatted_ranges.egg-info/PKG-INFO
formatted_ranges.egg-info/SOURCES.txt
formatted_ranges.egg-info/dependency_links.txt
formatted_ranges.egg-info/top_level.txt
ranges/__init__.py
ranges/date.py
ranges/parse.py
ranges/tests.py
ranges/types.py
ranges/utils.py